.coveragerc
.editorconfig
.flake8
.gitlab-ci.yml
.travis.yml
AUTHORS
CONTRIBUTING.rst
ChangeLog
LICENSE
MANIFEST.in
Makefile
README.rst
requirements.txt
requirements_dev.txt
setup.cfg
setup.py
tox.ini
.github/ISSUE_TEMPLATE.md
docs/Makefile
docs/source/conf.py
docs/source/index.rst
docs/source/installation.rst
docs/source/_static/style.css
docs/source/_templates/layout.html
esqb/__init__.py
esqb/docs_builder.py
esqb/drf_support.py
esqb/query.py
esqb/queryfilter.py
esqb/utils.py
esqb/variable.py
esqb.egg-info/PKG-INFO
esqb.egg-info/SOURCES.txt
esqb.egg-info/dependency_links.txt
esqb.egg-info/not-zip-safe
esqb.egg-info/pbr.json
esqb.egg-info/requires.txt
esqb.egg-info/top_level.txt
tests/__init__.py
tests/test_es_query_builder.py
tests/test_queryfilter.py