Metadata-Version: 2.1
Name: esqb
Version: 0.1.1
Summary: A Query Builder to build queries specially suited for ElasticSearch queries
Home-page: https://github.com/openshine/python-esqb
Author: Santiago Saavedra
Author-email: ssaavedra@openshine.com
License: UNKNOWN
Platform: UNKNOWN
Classifier: Development Status :: 3 - Alpha
Classifier: Intended Audience :: Developers
Classifier: Natural Language :: English
Classifier: Operating System :: OS Independent
Classifier: Programming Language :: Python :: 3
Classifier: Programming Language :: Python :: 3.4
Classifier: Programming Language :: Python :: 3.5
Classifier: Programming Language :: Python :: 3.6
Provides-Extra: drf
